sfmc/__init__.py
sfmc/client.py
sfmc/exceptions.py
sfmc/http.py
sfmc/util.py
sfmc/resources/__init__.py
sfmc/resources/account.py
sfmc/resources/business_unit.py
sfmc/resources/data_extension.py
sfmc/resources/email.py
sfmc/resources/events.py
sfmc/resources/filter.py
sfmc/resources/list.py
sfmc/resources/mixins.py
sfmc/resources/send.py
sfmc/resources/subscriber.py
sfmc-0.1.10.dist-info/DESCRIPTION.rst
sfmc-0.1.10.dist-info/METADATA
sfmc-0.1.10.dist-info/RECORD
sfmc-0.1.10.dist-info/WHEEL
sfmc-0.1.10.dist-info/metadata.json
sfmc-0.1.10.dist-info/top_level.txt
tests/unit/__init__.py
tests/unit/resources/__init__.py
tests/unit/resources/account.py
tests/unit/resources/business_unit.py
tests/unit/resources/data_extension.py
tests/unit/resources/email.py
tests/unit/resources/events.py
tests/unit/resources/list.py
tests/unit/resources/send.py
tests/unit/resources/subscriber.py
tests/unit/resources/test_data_extension.py
