Metadata-Version: 2.0
Name: sfmc
Version: 0.1.10
Summary: Salesforce Marketing Cloud client for Python
Home-page: https://github.com/6reduk/sfmc
Author: Dmitriy Shestakov
Author-email: 6reduk@gmail.com
License: MIT
Platform: UNKNOWN
Classifier: Intended Audience :: Developers
Classifier: License :: OSI Approved :: MIT License
Classifier: Operating System :: OS Independent
Classifier: Topic :: Software Development :: Libraries
Classifier: Programming Language :: Python :: 3.6
Requires-Dist: pyjwt (>=1.5.3)
Requires-Dist: requests (>=2.18.4)
Requires-Dist: lxml (==4.2.5)
Requires-Dist: suds-jurko (==0.6)
